streamlitfront/__init__.py
streamlitfront/base.py
streamlitfront/page_funcs.py
streamlitfront/session_state.py
streamlitfront/util.py
streamlitfront/examples/__init__.py
streamlitfront/examples/data_binding.py
streamlitfront/examples/experimentation.py
streamlitfront/examples/issues.py
streamlitfront/examples/kaggle_front.py
streamlitfront/examples/pos_key_args.py
streamlitfront/examples/simple.py
streamlitfront/examples/tw_data_binding.py
streamlitfront-0.0.2.dist-info/LICENSE
streamlitfront-0.0.2.dist-info/METADATA
streamlitfront-0.0.2.dist-info/WHEEL
streamlitfront-0.0.2.dist-info/top_level.txt
streamlitfront-0.0.2.dist-info/RECORD
